PortScout/__init__.py
PortScout/main.py
PortScout-1.0.2.dist-info/LICENSE
PortScout-1.0.2.dist-info/METADATA
PortScout-1.0.2.dist-info/WHEEL
PortScout-1.0.2.dist-info/entry_points.txt
PortScout-1.0.2.dist-info/top_level.txt
PortScout-1.0.2.dist-info/RECORD
