Metadata-Version: 2.1
Name: PortScout
Version: 1.0.2
Summary: A high-performance and efficient network port scanner for common ports. 
Home-page: https://github.com/MaulikxLakhani/PortScout
Author: Maulik Lakhani
Author-email: maulik.lakhanix@gmail.com
Classifier: Development Status :: 4 - Beta
Classifier: Intended Audience :: Developers
Classifier: Topic :: Software Development :: Build Tools
Classifier: License :: CC0 1.0 Universal (CC0 1.0) Public Domain Dedication
Classifier: Programming Language :: Python :: 3
Classifier: Programming Language :: Python :: 3.7
Classifier: Programming Language :: Python :: 3.8
Classifier: Programming Language :: Python :: 3.9
Classifier: Programming Language :: Python :: 3.10
Requires-Python: >=3.7
License-File: LICENSE
Requires-Dist: argparse
Requires-Dist: tabulate
